wheeledit/__init__.py
wheeledit/__main__.py
wheeledit/cli.py
wheeledit/editor.py
wheeledit-1.0.1.dist-info/licenses/LICENSE
wheeledit-1.0.1.dist-info/METADATA
wheeledit-1.0.1.dist-info/WHEEL
wheeledit-1.0.1.dist-info/entry_points.txt
wheeledit-1.0.1.dist-info/top_level.txt
wheeledit-1.0.1.dist-info/RECORD
