Metadata-Version: 2.4
Name: wheeledit
Version: 1.0.1
Summary: A tool for editing Python wheel packages
Author-email: Jack Zhou <jackzzs@outlook.com>
Project-URL: Homepage, https://github.com/zetxtech/wheeledit
Classifier: Programming Language :: Python :: 3
Classifier: License :: OSI Approved :: MIT License
Classifier: Operating System :: OS Independent
Requires-Python: >=3.6
License-File: LICENSE
Dynamic: license-file
